pytokr/__init__.py
pytokr-1.0.dist-info/LICENSE
pytokr-1.0.dist-info/METADATA
pytokr-1.0.dist-info/WHEEL
pytokr-1.0.dist-info/top_level.txt
pytokr-1.0.dist-info/RECORD
