Metadata-Version: 2.1
Name: pytokr
Version: 1.0
Summary: Very simple tokenizer for teaching purposes
Author-email: José Luis Balcázar <jose.luis.balcazar@upc.edu>
Project-URL: Homepage, https://github.com/balqui/pytokr
Project-URL: Bug Tracker, https://github.com/balqui/pytokr/issues
Classifier: Programming Language :: Python :: 3
Classifier: License :: OSI Approved :: MIT License
Classifier: Operating System :: OS Independent
Requires-Python: >=3.6
License-File: LICENSE
